{
    "name": "Tutorial",
    "currTid": 2,
    "order": true,
    "triggers":[
        {
            "tid":2,
            "triggerType":"Inventory",
            "triggerInfo":{
                "pid":0,
                "onLeave":false,
                "onEnter":true,
                "onAction":""
            },
            "triggerAction":{
                "type":"Dialogue",
                "tid":3,
                "pid":1,
                "tree":"Tutorial",
                "targetObj":""
            }
        },
        {
            "tid":3,
            "triggerType":"Inventory",
            "triggerInfo":{
                "pid":0,
                "onLeave":false,
                "onEnter":false,
                "onAction":"Size_Select"
            },
            "triggerAction":{
                "type":"Dialogue",
                "tid":4,
                "pid":2,
                "tree":"Tutorial",
                "targetObj":""
            }
        },
        {
            "tid":4,
            "triggerType":"Inventory",
            "triggerInfo":{
                "pid":0,
                "onLeave":false,
                "onEnter":false,
                "onAction":"Material_Select"
            },
            "triggerAction":{
                "type":"Dialogue",
                "tid":5,
                "pid":3,
                "tree":"Tutorial",
                "targetObj":""
            }
        },
        {
            "tid":5,
            "triggerType":"Inventory",
            "triggerInfo":{
                "pid":0,
                "onLeave":false,
                "onEnter":false,
                "onAction":"Type_Select"
            },
            "triggerAction":{
                "type":"Dialogue",
                "tid":6,
                "pid":5,
                "tree":"Tutorial",
                "targetObj":""
            }
        },
        {
            "tid":6,
            "triggerType":"Inventory",
            "triggerInfo":{
                "pid":0,
                "onLeave":false,
                "onEnter":false,
                "onAction":"Craft Success"
            },
            "triggerAction":{
                "type":"Dialogue",
                "tid":7,
                "pid":6,
                "tree":"Tutorial",
                "targetObj":""
            }
        },
        {
            "tid":7,
            "triggerType":"Inventory",
            "triggerInfo":{
                "pid":0,
                "onLeave":true,
                "onEnter":false,
                "onAction":""
            },
            "triggerAction":{
                "type":"Zoom",
                "sequence":"",
                "tid":8,
                "pid":7,
                "tree":"Tutorial",
                "targetObj":"Water Bottle"
            }
        },
        {
            "tid":8,
            "triggerType":"Player",
            "triggerInfo":{
                "pid":7,
                "onLeave":false,
                "onEnter":false,
                "onAction":"PickUp Water Bottle"
            },
            "triggerAction":{
                "type":"Dialogue",
                "sequence":"",
                "tid":9,
                "pid":8,
                "tree":"Tutorial",
                "targetObj":""
            }
        },
        {
            "tid":9,
            "triggerType":"Dialogue",
            "triggerInfo":{
                "pid":8,
                "onLeave":true,
                "onEnter":false,
                "onAction":""
            },
            "triggerAction":{
                "type":"changeSeq",
                "sequence":"Universal",
                "tid":0,
                "pid":0,
                "tree":"",
                "targetObj":""
            }
        }
    ]
}